<?xml version="1.0" encoding="UTF-8"?>
<mime-info xmlns="http://www.freedesktop.org/standards/shared-mime-info">
  <mime-type type="application/x-tanglet">
    <comment>Tanglet Game File</comment>
    <comment xml:lang="ca">Fitxer de joc Tanglet</comment>
    <comment xml:lang="cs">Soubor hry Tanglet</comment>
    <comment xml:lang="de">Tanglet-Spieldatei</comment>
    <comment xml:lang="el">Tanglet αρχείο παιχνιδιού</comment>
    <comment xml:lang="es">Archivo de juego Tanglet</comment>
    <comment xml:lang="fr">Fichier du jeu Tanglet</comment>
    <comment xml:lang="id">Berkas Game Tanglet</comment>
    <comment xml:lang="it">File di gioco Tanglet</comment>
    <comment xml:lang="lt">Tanglet žaidimo failas</comment>
    <comment xml:lang="ms">Fail Permainan Tanglet</comment>
    <comment xml:lang="nl">Tanglet spel bestand</comment>
    <comment xml:lang="pl">Plik gry Tanglet</comment>
    <comment xml:lang="pt">Ficheiro de Jogo Tanglet</comment>
    <comment xml:lang="ro">Fişier joc Tanglet</comment>
    <comment xml:lang="ru">Файл Игры Tanglet</comment>
    <comment xml:lang="tr">Tanglet Oyun Dosyası</comment>
    <comment xml:lang="uk">Файл гри Tanglet</comment>
    <glob pattern="*.tanglet"/>
  </mime-type>
</mime-info>
